amazonstoreprice/__init__.py
amazonstoreprice/amazonstoreprice.py
amazonstoreprice/exception.py
amazonstoreprice-0.1.7.dist-info/LICENSE
amazonstoreprice-0.1.7.dist-info/METADATA
amazonstoreprice-0.1.7.dist-info/WHEEL
amazonstoreprice-0.1.7.dist-info/top_level.txt
amazonstoreprice-0.1.7.dist-info/RECORD
