Metadata-Version: 2.1
Name: amazonstoreprice
Version: 0.1.7
Summary: Find the price on Amazon store starting from url
Home-page: https://github.com/Mirio/amazonstoreprice
Author: Alessandro Sbarbati
Author-email: miriodev@gmail.com
License: BSD
Download-URL: https://github.com/Mirio/amazonstoreprice/tarball/0.1
Keywords: Amazon,amazonprice,amazonstoreprice,amazonstore
Platform: UNKNOWN
Classifier: License :: OSI Approved :: BSD License
Classifier: Programming Language :: Python :: 3
Classifier: Topic :: Software Development :: Libraries :: Python Modules
Classifier: Topic :: Utilities
Requires-Dist: requests
Requires-Dist: beautifulsoup4
